Metadata-Version: 2.1
Name: light-telegram-bot
Version: 0.0.2
Summary: Light python module for telegram bot api
Home-page: https://github.com/Chebotarev-Alexey/light_telegram_bot
Author: Alexey Chebotarev
Author-email: alexey.p.chebotarev@gmail.com
License: UNKNOWN
Platform: UNKNOWN
Classifier: Programming Language :: Python :: 3.10
Classifier: Programming Language :: Python :: 3.9
Classifier: Programming Language :: Python :: 3.8
Classifier: Programming Language :: Python :: 3.7
Classifier: Programming Language :: Python :: 3.6
Classifier: License :: OSI Approved :: MIT License
Classifier: Operating System :: OS Independent
Requires-Python: >=3.8
License-File: LICENSE
